csv_converter_01/__init__.py
csv_converter_01/converter.py
csv_converter_01-0.9.1.dist-info/entry_points.txt
csv_converter_01-0.9.1.dist-info/WHEEL
csv_converter_01-0.9.1.dist-info/METADATA
csv_converter_01-0.9.1.dist-info/RECORD
